iva_applications/__init__.py
iva_applications/dequantization.py
iva_applications/offset_factory.py
iva_applications/preprocess_factory.py
iva_applications/albert_base/__init__.py
iva_applications/albert_base/calibration.py
iva_applications/albert_base/preprocess.py
iva_applications/alexnet/__init__.py
iva_applications/alexnet/calibration.py
iva_applications/alexnet/preprocess.py
iva_applications/arm/__init__.py
iva_applications/arm/calibration.py
iva_applications/arm/preprocess.py
iva_applications/bert_large/__init__.py
iva_applications/bert_large/calibration.py
iva_applications/bert_large/preprocess.py
iva_applications/covidnet_cxr4_a/__init__.py
iva_applications/covidnet_cxr4_a/calibration.py
iva_applications/covidnet_cxr4_a/preprocess.py
iva_applications/dcgan/__init__.py
iva_applications/dcgan/calibration.py
iva_applications/dcgan/postprocess.py
iva_applications/densenet121/__init__.py
iva_applications/densenet121/calibration.py
iva_applications/densenet121/preprocess.py
iva_applications/efficientnet_b1/__init__.py
iva_applications/efficientnet_b1/calibration.py
iva_applications/efficientnet_b1/preprocess.py
iva_applications/efficientnet_b2/__init__.py
iva_applications/efficientnet_b2/calibration.py
iva_applications/efficientnet_b2/preprocess.py
iva_applications/efficientnet_b3/__init__.py
iva_applications/efficientnet_b3/calibration.py
iva_applications/efficientnet_b3/preprocess.py
iva_applications/efficientnet_b4/__init__.py
iva_applications/efficientnet_b4/calibration.py
iva_applications/efficientnet_b4/preprocess.py
iva_applications/efficientnet_b5/__init__.py
iva_applications/efficientnet_b5/calibration.py
iva_applications/efficientnet_b5/preprocess.py
iva_applications/gpt2/__init__.py
iva_applications/gpt2/calibration.py
iva_applications/gpt2/preprocess.py
iva_applications/imagenet/__init__.py
iva_applications/imagenet/config.py
iva_applications/imagenet/images_utils.py
iva_applications/imagenet/postprocess.py
iva_applications-11.0.1.dist-info/LICENSE
iva_applications-11.0.1.dist-info/METADATA
iva_applications-11.0.1.dist-info/WHEEL
iva_applications-11.0.1.dist-info/top_level.txt
iva_applications-11.0.1.dist-info/RECORD
